AUTHORS.rst
CHANGELOG.rst
LICENSE
MANIFEST.in
README.rst
setup.py
jmbo_listing.egg-info/PKG-INFO
jmbo_listing.egg-info/SOURCES.txt
jmbo_listing.egg-info/dependency_links.txt
jmbo_listing.egg-info/not-zip-safe
jmbo_listing.egg-info/requires.txt
jmbo_listing.egg-info/top_level.txt
listing/__init__.py
listing/admin.py
listing/managers.py
listing/models.py
listing/styles.py
listing/urls.py
listing/views.py
listing/api/__init__.py
listing/fixtures/photosizes.json
listing/migrations/0001_initial.py
listing/migrations/0001_initial.pyc
listing/migrations/__init__.py
listing/migrations/__init__.pyc
listing/static/admin/listing/images/custom-five.png
listing/static/admin/listing/images/custom-four.png
listing/static/admin/listing/images/custom-one.png
listing/static/admin/listing/images/custom-three.png
listing/static/admin/listing/images/custom-two.png
listing/static/admin/listing/images/horizontal.png
listing/static/admin/listing/images/promo.png
listing/static/admin/listing/images/tile.png
listing/static/admin/listing/images/unknown.png
listing/static/admin/listing/images/vertical-thumbnail.png
listing/static/admin/listing/images/vertical.png
listing/static/admin/listing/images/widget.png
listing/templates/jmbo/inclusion_tags/modelbase_listing_item.html
listing/templates/jmbo/inclusion_tags/modelbase_listing_item_ipod.html
listing/templates/jmbo/inclusion_tags/modelbase_listing_item_ipod_pinned.html
listing/templates/jmbo/inclusion_tags/modelbase_listing_item_pinned.html
listing/templates/jmbo/inclusion_tags/modelbase_listing_item_promo.html
listing/templates/jmbo/inclusion_tags/modelbase_listing_item_promo_pinned.html
listing/templates/jmbo/inclusion_tags/modelbase_listing_item_thumbnail.html
listing/templates/jmbo/inclusion_tags/modelbase_listing_item_thumbnail_pinned.html
listing/templates/jmbo/inclusion_tags/modelbase_listing_item_widget.html
listing/templates/jmbo/inclusion_tags/modelbase_listing_item_widget_pinned.html
listing/templates/listing/listing_detail.html
listing/templates/listing/templatetags/custom_five.html
listing/templates/listing/templatetags/custom_four.html
listing/templates/listing/templatetags/custom_one.html
