Metadata-Version: 1.1
Name: jmbo-listing
Version: 0.1.1
Summary: A listing is a stored search that can be rendered in a certain style.
Home-page: https://github.com/praekelt/jmbo-listing
Author: Praekelt Consulting
Author-email: dev@praekelt.com
License: BSD
Platform: UNKNOWN
Classifier: Programming Language :: Python
Classifier: License :: OSI Approved :: BSD License
Classifier: Development Status :: 5 - Production/Stable
Classifier: Operating System :: OS Independent
Classifier: Framework :: Django
Classifier: Intended Audience :: Developers
Classifier: Topic :: Internet :: WWW/HTTP :: Dynamic Content
